JK_FF/jk_ff_behav.v
module jk_ff(input j, input k, 
  	    input clk, output q);   
reg q;  
 always @ (posedge clk)  
   case ({j,k})  
      2'b00 :  q <= q;  
      2'b01 :  q <= 0;  
      2'b10 :  q <= 1;  
      2'b11 :  q <= ~q;  
   endcase  
endmodule  

module jk_ff_test;
reg J, K, iCLK;
wire Q, Qb;
integer i;

jk_ff jkff(J, K, iCLK, Q); // instantiation by port name.


initial begin
     iCLK=0;
     for(i=0;i<10; i++) begin 
	     #10; iCLK = ~iCLK;
	     $display("iCLK = %b, J = %b, K = %b, Q = %b", iCLK, J, K, Q);
     end
end
initial begin
$dumpfile("jk_ff.vcd");
$dumpvars;
     	J <= 0;  K <= 0;    
  #5 	J <= 0;  K <= 1;  
  #20 	J <= 1;  K <= 0;  
  #20   J <= 1;  K <= 1;  
  #20   $finish;  
end
endmodule

JK_FF/jk_ff.vcd
$date
	Tue Nov  7 18:41:13 2023
$end
$version
	Icarus Verilog
$end
$timescale
	1s
$end
$scope module jk_ff_test $end
$var wire 1 ! Q $end
$var reg 1 " J $end
$var reg 1 # K $end
$var reg 1 $ iCLK $end
$var integer 32 % i [31:0] $end
$scope module jkff $end
$var wire 1 $ clk $end
$var wire 1 " j $end
$var wire 1 # k $end
$var reg 1 ! q $end
$upscope $end
$upscope $end
$enddefinitions $end
#0
$dumpvars
b0 %
0$
0#
0"
x!
$end
#5
1#
#10
0!
b1 %
1$
#20
b10 %
0$
#25
0#
1"
#30
1!
b11 %
1$
#40
b100 %
0$
#45
1#
#50
0!
b101 %
1$
#60
b110 %
0$
